LICENSE
MANIFEST.in
README.md
setup.cfg
setup.py
flint_python_executor_handler.egg-info/PKG-INFO
flint_python_executor_handler.egg-info/SOURCES.txt
flint_python_executor_handler.egg-info/dependency_links.txt
flint_python_executor_handler.egg-info/requires.txt
flint_python_executor_handler.egg-info/top_level.txt
handler/__init__.py
handler/flow_data.py
handler/handler_helper.py
handler/model.py
handler/version.py