Metadata-Version: 1.1
Name: flint-python-executor-handler
Version: 0.1.1
Summary: flint python executor handler
Home-page: https://github.com/flintdev/flint-python-executor-handler
Author: Gaoxin Dai
Author-email: daigx1990@gmail.com
License: Apache License 2.0
Platform: UNKNOWN
Classifier: Development Status :: 5 - Production/Stable
Classifier: Intended Audience :: Developers
Classifier: License :: OSI Approved :: Apache Software License
Classifier: Programming Language :: Python
Classifier: Programming Language :: Python :: 2
Classifier: Programming Language :: Python :: 3
